atshop/__init__.py
atshop/api.py
atshop/endpoints.py
atshop-1.0.0.dist-info/METADATA
atshop-1.0.0.dist-info/WHEEL
atshop-1.0.0.dist-info/top_level.txt
atshop-1.0.0.dist-info/RECORD
