Metadata-Version: 2.1
Name: atshop
Version: 1.0.0
Summary: A Python wrapper for the Atshop API
Home-page: https://github.com/iclapcheeks/Atshop
Author: iclapcheeks
Author-email: iclapcheeeeeks@protonmail.com
License: UNKNOWN
Platform: UNKNOWN
Requires-Python: ~=3.7
Requires-Dist: websocket-client (>=1.3.3)
